<?xml version="1.0" encoding="utf-8"?>

<!--

  Name   : Jornalero Residences Provide Influence
  Author : adjagu
  License: GPL-2.0-only
  Version: 0.1.3

  Please refer to README.txt for more information.

-->

<ModOps>

  <!--

    Jornalero Residence (Jornalero-​Haus)

  -->
  <ModOp GUID="101254" Path="/Values/InfluenceSource" Type="Merge"
    ModOpID="JornaleroInfluenceAmount"
  >
    <InfluenceAmount>1</InfluenceAmount>
    <InfluenceSource>Culture</InfluenceSource>
  </ModOp>

  <!--

    iModYourAnno Tweaking : Title

  -->
  <ImyaTweaks Title="Jornalero" />

  <!--

    iModYourAnno Tweaking : Tweak
    Jornalero Residence (Jornalero-​Haus)

  -->
  <ImyaExpose
    Path="self::InfluenceAmount"
    ModOpID="JornaleroInfluenceAmount"
    ExposeID="Jornalero"
    Description="Influence per jornalero residence."
    Kind="Slider"
  >
    <SliderDefinition Min="0" Max="100" Stepping="1" />
  </ImyaExpose>

  <!--

    How about a little space for the closing tag?

  -->

</ModOps>